LICENSE
MANIFEST.in
README.md
setup.py
./requirements.txt
kot_run/__init__.py
kot_run/kot_run.py
kot_run.egg-info/PKG-INFO
kot_run.egg-info/SOURCES.txt
kot_run.egg-info/dependency_links.txt
kot_run.egg-info/not-zip-safe
kot_run.egg-info/requires.txt
kot_run.egg-info/top_level.txt