Metadata-Version: 2.1
Name: kot-run
Version: 0.3.2
Summary: The cloud python function runner !
Home-page: https://github.com/KOT-database/KOT-Run
Author: Onur Atakan ULUSOY
Author-email: atadogan06@gmail.com
License: MIT
Platform: UNKNOWN
Requires-Python: >= 3
